tenantflow/__init__.py
tenantflow/middleware.py
tenantflow/utils.py
tenantflow/management/__init__.py
tenantflow/management/commands/__init__.py
tenantflow/management/commands/create_tenant.py
tenantflow/management/commands/create_tenant_superuser.py
tenantflow/management/commands/delete_tenant.py
tenantflow/management/commands/migrate_schemas.py
tenantflow/models/__init__.py
tenantflow/models/account.py
tenantflow/models/user_account.py
django_tenantflow-1.0.12.dist-info/LICENSE
django_tenantflow-1.0.12.dist-info/METADATA
django_tenantflow-1.0.12.dist-info/WHEEL
django_tenantflow-1.0.12.dist-info/top_level.txt
django_tenantflow-1.0.12.dist-info/RECORD
