Metadata-Version: 2.1
Name: django-tenantflow
Version: 1.0.12
Summary: A Django library to enable semi-isolated multitenancy in your project with users outside the tenant.
Home-page: https://github.com/ConspiraciXn/django-tenantflow
Author: Jared Soto
Author-email: jared.sl@icloud.com
License: MIT
Classifier: Framework :: Django
Classifier: Programming Language :: Python :: 3.12
Classifier: License :: OSI Approved :: MIT License
License-File: LICENSE
Requires-Dist: django>=5.0
Requires-Dist: psycopg2-binary
